pyCitizenBand/__init__.py
pyCitizenBand/version.py
pyCitizenBand-0.0.1.dist-info/DESCRIPTION.rst
pyCitizenBand-0.0.1.dist-info/METADATA
pyCitizenBand-0.0.1.dist-info/RECORD
pyCitizenBand-0.0.1.dist-info/WHEEL
pyCitizenBand-0.0.1.dist-info/metadata.json
pyCitizenBand-0.0.1.dist-info/pbr.json
pyCitizenBand-0.0.1.dist-info/top_level.txt
