Metadata-Version: 2.0
Name: pyCitizenBand
Version: 0.0.1
Summary: A Python package with some useful function for Citizen Band users, DXers, ...
Home-page: https://github.com/scls19fr/pyCitizenBand
Author: Sebastien Celles
Author-email: s.celles@gmail.com
License: GPL
Keywords: python pandas numpy radio ham radioham cb citizen band citizenband
Platform: UNKNOWN
Classifier: Development Status :: 3 - Alpha
Classifier: Environment :: Console
Classifier: Intended Audience :: Developers
Classifier: Operating System :: OS Independent
Classifier: Programming Language :: Cython
Classifier: Programming Language :: Python
Classifier: Programming Language :: Python :: 2.7
Classifier: Programming Language :: Python :: 3.3
Classifier: Programming Language :: Python :: 3.4
Classifier: License :: OSI Approved :: GNU General Public License v3 or later (GPLv3+)
Requires-Dist: pandas
Provides-Extra: dev
Requires-Dist: check-manifest; extra == 'dev'
Requires-Dist: nose; extra == 'dev'
Provides-Extra: test
Requires-Dist: coverage; extra == 'test'
Requires-Dist: nose; extra == 'test'
